LICENSE
MANIFEST.in
README.md
setup.py
pyvcgencmd/__init__.py
pyvcgencmd/__version__.py
pyvcgencmd/core.py
pyvcgencmd/exceptions.py
pyvcgencmd/help.py
pyvcgencmd/main.py
pyvcgencmd/models.py
pyvcgencmd/utils.py
pyvcgencmd.egg-info/PKG-INFO
pyvcgencmd.egg-info/SOURCES.txt
pyvcgencmd.egg-info/dependency_links.txt
pyvcgencmd.egg-info/not-zip-safe
pyvcgencmd.egg-info/requires.txt
pyvcgencmd.egg-info/top_level.txt