Metadata-Version: 2.1
Name: pyvcgencmd
Version: 0.0.4
Summary: Python Wrapper for BCM (Raspberry Pi) vcgencmd
Home-page: https://github.com/AzatAI/vcgencmd
Author: Yaakov Azat
Author-email: yaakovazat@gmail.com
License: MIT
Project-URL: Documentation, https://github.com/AzatAI/pyvcgencmd
Project-URL: Source, https://github.com/AzatAI/pyvcgencmd
Platform: UNKNOWN
Classifier: Development Status :: 5 - Production/Stable
Classifier: Intended Audience :: Developers
Classifier: Natural Language :: English
Classifier: Programming Language :: Python
Classifier: Programming Language :: Python :: 3
Classifier: Programming Language :: Python :: 3.6
Classifier: Programming Language :: Python :: 3.7
Classifier: Programming Language :: Python :: 3.8
Classifier: Programming Language :: Python :: 3.9
Classifier: Programming Language :: Python :: 3.10
Classifier: Programming Language :: Python :: Implementation :: CPython
Classifier: Programming Language :: Python :: Implementation :: PyPy
Requires-Python: >=3.6
License-File: LICENSE
